FluoSA/COPYRIGHT.txt
FluoSA/NOTICE.txt
FluoSA/__init__.py
FluoSA/__main__.py
FluoSA/analyzer.py
FluoSA/detector.py
FluoSA/detectors/__init__.py
FluoSA/gui.py
fluosa-1.0.0.dist-info/METADATA
fluosa-1.0.0.dist-info/WHEEL
fluosa-1.0.0.dist-info/entry_points.txt
fluosa-1.0.0.dist-info/licenses/LICENSE.txt
fluosa-1.0.0.dist-info/licenses/NOTICE.txt
fluosa-1.0.0.dist-info/RECORD
