Metadata-Version: 2.1
Name: FluoSA
Version: 1.0.0
Summary: Fluorescence Signal Analyzer for calcium imaging on user-defined neural structures.
Keywords: Fluorescence signal analysis,Calcium imaging analysis
Author-Email: Yujia Hu <yujiahu415@gmail.com>
License: GPL-3.0
Classifier: License :: OSI Approved :: GNU General Public License v3 (GPLv3)
Classifier: Operating System :: OS Independent
Classifier: Programming Language :: Python :: 3
Classifier: Programming Language :: Python :: 3 :: Only
Classifier: Programming Language :: Python :: 3.9
Classifier: Programming Language :: Python :: 3.10
Project-URL: Homepage, https://github.com/umyelab/FluoSA
Requires-Python: <3.11,>=3.9
Requires-Dist: numpy<=1.26.4
Requires-Dist: scipy
Requires-Dist: readlif
Requires-Dist: tifffile
Requires-Dist: opencv-python
Requires-Dist: opencv-contrib-python
Requires-Dist: openpyxl
Requires-Dist: xlsxwriter
Requires-Dist: pandas
Requires-Dist: wxPython
Requires-Dist: packaging
Requires-Dist: requests
Requires-Dist: torch
Requires-Dist: torchvision
Requires-Dist: torchaudio
